{
  "id": "com.nodalcore.remote-io-dashboard",
  "name": "Remote IO Dashboard",
  "version": "0.2.0",
  "sdkVersion": "^0.2.0",
  "type": "device-bridge",
  "main": "dist/index.js",
  "connectionType": "tcp",
  "permissions": ["network"],
  "contributes": {
    "configuration": {
      "title": "Remote IO Settings",
      "properties": {
        "host": {
          "type": "string",
          "title": "Device IP",
          "default": "192.168.1.10"
        },
        "portOffset": {
          "type": "integer",
          "title": "Port Offset",
          "description": "Effective TCP port = 8500 + offset",
          "default": 0,
          "minimum": 0,
          "maximum": 65035
        }
      }
    },
    "views": {
      "panel": [
        { "id": "dashboard", "name": "Live Dashboard", "html": "panel/index.html" }
      ]
    }
  },
  "author": "Remote IO Dashboard",
  "tags": ["io", "tcp", "hardware", "zephyr"]
}
